medusa/__init__.py
medusa/__main__.py
medusa/assets.py
medusa/build.py
medusa/cli.py
medusa/collections.py
medusa/content.py
medusa/server.py
medusa/templates.py
medusa/utils.py
medusa/templates/default/.gitignore
medusa/templates/default/README.md
medusa/templates/default/llms.txt
medusa/templates/default/medusa.yaml
medusa/templates/default/tailwind.config.js
medusa/templates/default/assets/css/main.css
medusa/templates/default/assets/css/pygments.css
medusa/templates/default/assets/fonts/.keep
medusa/templates/default/assets/images/.keep
medusa/templates/default/assets/js/.keep
medusa/templates/default/assets/js/main.js
medusa/templates/default/data/nav.yaml
medusa/templates/default/data/site.yaml
medusa/templates/default/site/404.html
medusa/templates/default/site/about.md
medusa/templates/default/site/index.jinja
medusa/templates/default/site/_layouts/default.html.jinja
medusa/templates/default/site/_partials/footer.html.jinja
medusa/templates/default/site/_partials/header.html.jinja
medusa/templates/default/site/posts/2024-01-01-features.md
medusa/templates/default/site/posts/2024-01-02-install.md
medusa/templates/default/site/posts/2024-01-03-usage.md
medusa/templates/default/site/posts/2024-01-04-data-in-templates.md
medusa/templates/default/site/posts/2024-01-05-examples.md
medusa/templates/default/site/posts/2024-01-06-project-layout.md
medusa/templates/default/site/posts/2024-01-07-development.md
medusa/templates/default/site/posts/2024-01-08-notes.md
medusa/templates/default/site/posts/2024-01-09-asset-helpers.md
medusa/templates/default/site/posts/index.jinja
medusa_ssg-0.1.9.dist-info/licenses/LICENSE
medusa_ssg-0.1.9.dist-info/METADATA
medusa_ssg-0.1.9.dist-info/WHEEL
medusa_ssg-0.1.9.dist-info/entry_points.txt
medusa_ssg-0.1.9.dist-info/top_level.txt
medusa_ssg-0.1.9.dist-info/RECORD
