Metadata-Version: 2.4
Name: medusa-ssg
Version: 0.1.9
Summary: Minimal Python static site generator. Markdown + Jinja2, Tailwind CSS built-in, zero configuration, no frontmatter.
Author: wusher
License: MIT
Project-URL: Homepage, https://github.com/yourname/medusa-ssg
Project-URL: Repository, https://github.com/yourname/medusa-ssg
Project-URL: Issues, https://github.com/yourname/medusa-ssg/issues
Project-URL: Documentation, https://github.com/yourname/medusa-ssg#readme
Keywords: static-site-generator,ssg,markdown,jinja2,tailwind,blog,website
Classifier: Development Status :: 4 - Beta
Classifier: Environment :: Console
Classifier: Intended Audience :: Developers
Classifier: License :: OSI Approved :: MIT License
Classifier: Operating System :: OS Independent
Classifier: Programming Language :: Python :: 3
Classifier: Programming Language :: Python :: 3.10
Classifier: Programming Language :: Python :: 3.11
Classifier: Programming Language :: Python :: 3.12
Classifier: Topic :: Internet :: WWW/HTTP :: Site Management
Classifier: Topic :: Text Processing :: Markup :: Markdown
Requires-Python: >=3.10
License-File: LICENSE
Requires-Dist: click>=8.1
Requires-Dist: jinja2>=3.1
Requires-Dist: mistune>=3.0
Requires-Dist: pygments>=2.17
Requires-Dist: pyyaml>=6.0
Requires-Dist: questionary>=2.0
Requires-Dist: watchdog>=4.0
Requires-Dist: websockets>=12.0
Requires-Dist: rjsmin>=1.2
Requires-Dist: pillow>=10.0
Provides-Extra: dev
Requires-Dist: pytest>=7.0; extra == "dev"
Requires-Dist: pytest-cov>=4.0; extra == "dev"
Requires-Dist: ruff>=0.8.0; extra == "dev"
Dynamic: license-file
